[
    {
        "confidence": [
            0.023134350776672363,
            0.9768656492233276
        ],
        "ethnicity": "other",
        "name": "Aban"
    },
    {
        "confidence": [
            0.023203253746032715,
            0.9767968058586121
        ],
        "ethnicity": "other",
        "name": "Abbud"
    },
    {
        "confidence": [
            0.023138701915740967,
            0.9768612384796143
        ],
        "ethnicity": "other",
        "name": "Abd al bari"
    },
    {
        "confidence": [
            0.023131072521209717,
            0.9768689274787903
        ],
        "ethnicity": "other",
        "name": "Abd al rahman"
    },
    {
        "confidence": [
            0.023131072521209717,
            0.9768689274787903
        ],
        "ethnicity": "other",
        "name": "Abd al samad"
    },
    {
        "confidence": [
            0.02313128113746643,
            0.976868748664856
        ],
        "ethnicity": "other",
        "name": "Abdel"
    },
    {
        "confidence": [
            0.023131072521209717,
            0.9768689274787903
        ],
        "ethnicity": "other",
        "name": "Abu bakr"
    },
    {
        "confidence": [
            0.023163974285125732,
            0.9768360257148743
        ],
        "ethnicity": "other",
        "name": "Adil"
    },
    {
        "confidence": [
            0.02313181757926941,
            0.976868212223053
        ],
        "ethnicity": "other",
        "name": "Adnan"
    },
    {
        "confidence": [
            0.023144453763961792,
            0.9768555164337158
        ],
        "ethnicity": "other",
        "name": "Afiya"
    },
    {
        "confidence": [
            0.9720877408981323,
            0.02791231870651245
        ],
        "ethnicity": "white",
        "name": "Ahmad"
    },
    {
        "confidence": [
            0.023131072521209717,
            0.9768689274787903
        ],
        "ethnicity": "other",
        "name": "Akram"
    },
    {
        "confidence": [
            0.023746401071548462,
            0.9762536287307739
        ],
        "ethnicity": "other",
        "name": "Alaqa"
    },
    {
        "confidence": [
            0.029480189085006714,
            0.9705197811126709
        ],
        "ethnicity": "other",
        "name": "Ali"
    },
    {
        "confidence": [
            0.13423040509223938,
            0.865769624710083
        ],
        "ethnicity": "other",
        "name": "Alim"
    },
    {
        "confidence": [
            0.023131072521209717,
            0.9768689274787903
        ],
        "ethnicity": "other",
        "name": "Altair"
    },
    {
        "confidence": [
            0.023135632276535034,
            0.9768644571304321
        ],
        "ethnicity": "other",
        "name": "Alyas"
    },
    {
        "confidence": [
            0.028532415628433228,
            0.9714676141738892
        ],
        "ethnicity": "other",
        "name": "Ameen"
    },
    {
        "confidence": [
            0.023189812898635864,
            0.9768102169036865
        ],
        "ethnicity": "other",
        "name": "Amin"
    },
    {
        "confidence": [
            0.023131072521209717,
            0.9768689274787903
        ],
        "ethnicity": "other",
        "name": "Amjad"
    },
    {
        "confidence": [
            0.023142844438552856,
            0.9768571257591248
        ],
        "ethnicity": "other",
        "name": "Ammar"
    },
    {
        "confidence": [
            0.023131132125854492,
            0.9768688678741455
        ],
        "ethnicity": "other",
        "name": "Anwar"
    },
    {
        "confidence": [
            0.02313166856765747,
            0.9768683910369873
        ],
        "ethnicity": "other",
        "name": "Arash"
    },
    {
        "confidence": [
            0.024450451135635376,
            0.975549578666687
        ],
        "ethnicity": "other",
        "name": "Arif"
    },
    {
        "confidence": [
            0.026818275451660156,
            0.9731817245483398
        ],
        "ethnicity": "other",
        "name": "Arqa"
    },
    {
        "confidence": [
            0.023131072521209717,
            0.9768689274787903
        ],
        "ethnicity": "other",
        "name": "Asad"
    },
    {
        "confidence": [
            0.023131072521209717,
            0.9768689274787903
        ],
        "ethnicity": "other",
        "name": "Ashraf"
    },
    {
        "confidence": [
            0.15559402108192444,
            0.8444058895111084
        ],
        "ethnicity": "other",
        "name": "Asim"
    },
    {
        "confidence": [
            0.023131072521209717,
            0.9768689274787903
        ],
        "ethnicity": "other",
        "name": "Aswad"
    },
    {
        "confidence": [
            0.02313295006752014,
            0.9768669605255127
        ],
        "ethnicity": "other",
        "name": "Ata"
    },
    {
        "confidence": [
            0.023132115602493286,
            0.9768679141998291
        ],
        "ethnicity": "other",
        "name": "Ayyub"
    },
    {
        "confidence": [
            0.02313309907913208,
            0.9768668413162231
        ],
        "ethnicity": "other",
        "name": "Azam"
    },
    {
        "confidence": [
            0.023131072521209717,
            0.9768689274787903
        ],
        "ethnicity": "other",
        "name": "Azim"
    },
    {
        "confidence": [
            0.023131221532821655,
            0.976868748664856
        ],
        "ethnicity": "other",
        "name": "Aziz"
    },
    {
        "confidence": [
            0.02352273464202881,
            0.9764772653579712
        ],
        "ethnicity": "other",
        "name": "Badr al din"
    },
    {
        "confidence": [
            0.023131072521209717,
            0.9768689274787903
        ],
        "ethnicity": "other",
        "name": "Bahi"
    },
    {
        "confidence": [
            0.023131072521209717,
            0.9768689274787903
        ],
        "ethnicity": "other",
        "name": "Bahram"
    },
    {
        "confidence": [
            0.023134499788284302,
            0.9768654108047485
        ],
        "ethnicity": "other",
        "name": "Barakah"
    },
    {
        "confidence": [
            0.023131072521209717,
            0.9768689274787903
        ],
        "ethnicity": "other",
        "name": "Bashshar"
    },
    {
        "confidence": [
            0.023131072521209717,
            0.9768689274787903
        ],
        "ethnicity": "other",
        "name": "Basil"
    },
    {
        "confidence": [
            0.023131221532821655,
            0.976868748664856
        ],
        "ethnicity": "other",
        "name": "Bassaym"
    },
    {
        "confidence": [
            0.024828046560287476,
            0.9751720428466797
        ],
        "ethnicity": "other",
        "name": "Bassma"
    },
    {
        "confidence": [
            0.023131072521209717,
            0.9768689274787903
        ],
        "ethnicity": "other",
        "name": "Behrooz"
    },
    {
        "confidence": [
            0.02314096689224243,
            0.9768590331077576
        ],
        "ethnicity": "other",
        "name": "Behzad"
    },
    {
        "confidence": [
            0.023929566144943237,
            0.9760704040527344
        ],
        "ethnicity": "other",
        "name": "Bishr"
    },
    {
        "confidence": [
            0.02315649390220642,
            0.9768434762954712
        ],
        "ethnicity": "other",
        "name": "Borak"
    },
    {
        "confidence": [
            0.023148566484451294,
            0.9768514037132263
        ],
        "ethnicity": "other",
        "name": "Butrus"
    },
    {
        "confidence": [
            0.023142844438552856,
            0.9768571257591248
        ],
        "ethnicity": "other",
        "name": "Cairo"
    },
    {
        "confidence": [
            0.023134559392929077,
            0.9768655300140381
        ],
        "ethnicity": "other",
        "name": "Casildo"
    },
    {
        "confidence": [
            0.028355658054351807,
            0.971644401550293
        ],
        "ethnicity": "other",
        "name": "Casper"
    },
    {
        "confidence": [
            0.9724581241607666,
            0.0275418758392334
        ],
        "ethnicity": "white",
        "name": "Chakir"
    },
    {
        "confidence": [
            0.026044100522994995,
            0.9739558696746826
        ],
        "ethnicity": "other",
        "name": "Chelem"
    },
    {
        "confidence": [
            0.14221838116645813,
            0.8577816486358643
        ],
        "ethnicity": "other",
        "name": "Cyrus"
    },
    {
        "confidence": [
            0.023297518491744995,
            0.9767025709152222
        ],
        "ethnicity": "other",
        "name": "Dabir"
    },
    {
        "confidence": [
            0.217036634683609,
            0.7829633951187134
        ],
        "ethnicity": "other",
        "name": "Darioush"
    },
    {
        "confidence": [
            0.023131072521209717,
            0.9768689274787903
        ],
        "ethnicity": "other",
        "name": "Dawud"
    },
    {
        "confidence": [
            0.023131221532821655,
            0.976868748664856
        ],
        "ethnicity": "other",
        "name": "Diya al din"
    },
    {
        "confidence": [
            0.9732869863510132,
            0.02671298384666443
        ],
        "ethnicity": "white",
        "name": "Durward"
    },
    {
        "confidence": [
            0.023131072521209717,
            0.9768689274787903
        ],
        "ethnicity": "other",
        "name": "Emir"
    },
    {
        "confidence": [
            0.02600899338722229,
            0.9739910364151001
        ],
        "ethnicity": "other",
        "name": "Fadahunsi"
    },
    {
        "confidence": [
            0.025288254022598267,
            0.9747117757797241
        ],
        "ethnicity": "other",
        "name": "Fadel"
    },
    {
        "confidence": [
            0.023131102323532104,
            0.9768688678741455
        ],
        "ethnicity": "other",
        "name": "Fadi"
    },
    {
        "confidence": [
            0.023131132125854492,
            0.9768688678741455
        ],
        "ethnicity": "other",
        "name": "Fadil"
    },
    {
        "confidence": [
            0.023501932621002197,
            0.9764981269836426
        ],
        "ethnicity": "other",
        "name": "Fahd"
    },
    {
        "confidence": [
            0.02457079291343689,
            0.9754291772842407
        ],
        "ethnicity": "other",
        "name": "Fakhir"
    },
    {
        "confidence": [
            0.024084001779556274,
            0.9759160876274109
        ],
        "ethnicity": "other",
        "name": "Fakih"
    },
    {
        "confidence": [
            0.02313244342803955,
            0.9768676161766052
        ],
        "ethnicity": "other",
        "name": "Farhan"
    },
    {
        "confidence": [
            0.023131072521209717,
            0.9768689274787903
        ],
        "ethnicity": "other",
        "name": "Farid"
    },
    {
        "confidence": [
            0.023179471492767334,
            0.9768205881118774
        ],
        "ethnicity": "other",
        "name": "Faris"
    },
    {
        "confidence": [
            0.02392512559890747,
            0.9760749340057373
        ],
        "ethnicity": "other",
        "name": "Faruq"
    },
    {
        "confidence": [
            0.025522947311401367,
            0.9744770526885986
        ],
        "ethnicity": "other",
        "name": "Fath"
    },
    {
        "confidence": [
            0.023131072521209717,
            0.9768689274787903
        ],
        "ethnicity": "other",
        "name": "Fatin"
    },
    {
        "confidence": [
            0.023736238479614258,
            0.9762637615203857
        ],
        "ethnicity": "other",
        "name": "Feroz"
    },
    {
        "confidence": [
            0.03364604711532593,
            0.9663538932800293
        ],
        "ethnicity": "other",
        "name": "Ferran"
    },
    {
        "confidence": [
            0.024815410375595093,
            0.9751846790313721
        ],
        "ethnicity": "other",
        "name": "Firas"
    },
    {
        "confidence": [
            0.023757487535476685,
            0.9762425422668457
        ],
        "ethnicity": "other",
        "name": "Fudail"
    },
    {
        "confidence": [
            0.023131996393203735,
            0.9768680334091187
        ],
        "ethnicity": "other",
        "name": "Ghalib"
    },
    {
        "confidence": [
            0.023131072521209717,
            0.9768689274787903
        ],
        "ethnicity": "other",
        "name": "Ghassan"
    },
    {
        "confidence": [
            0.023131072521209717,
            0.9768689274787903
        ],
        "ethnicity": "other",
        "name": "Ghazi"
    },
    {
        "confidence": [
            0.02453291416168213,
            0.9754670858383179
        ],
        "ethnicity": "other",
        "name": "Gilad"
    },
    {
        "confidence": [
            0.023131072521209717,
            0.9768689274787903
        ],
        "ethnicity": "other",
        "name": "Habib"
    },
    {
        "confidence": [
            0.13906913995742798,
            0.8609308004379272
        ],
        "ethnicity": "other",
        "name": "Haddad"
    },
    {
        "confidence": [
            0.023574471473693848,
            0.9764255881309509
        ],
        "ethnicity": "other",
        "name": "Hadi"
    },
    {
        "confidence": [
            0.023266136646270752,
            0.9767338037490845
        ],
        "ethnicity": "other",
        "name": "Hakeem"
    },
    {
        "confidence": [
            0.02313283085823059,
            0.976867139339447
        ],
        "ethnicity": "other",
        "name": "Hakim"
    },
    {
        "confidence": [
            0.023153334856033325,
            0.9768466949462891
        ],
        "ethnicity": "other",
        "name": "Hamal"
    },
    {
        "confidence": [
            0.039536088705062866,
            0.9604638814926147
        ],
        "ethnicity": "other",
        "name": "Hamid"
    },
    {
        "confidence": [
            0.02316555380821228,
            0.9768344163894653
        ],
        "ethnicity": "other",
        "name": "Hanbal"
    },
    {
        "confidence": [
            0.032701343297958374,
            0.9672986268997192
        ],
        "ethnicity": "other",
        "name": "Hanif"
    },
    {
        "confidence": [
            0.9732869863510132,
            0.02671298384666443
        ],
        "ethnicity": "white",
        "name": "Harith"
    },
    {
        "confidence": [
            0.9674090147018433,
            0.03259095549583435
        ],
        "ethnicity": "white",
        "name": "Haroun"
    },
    {
        "confidence": [
            0.023189812898635864,
            0.9768102169036865
        ],
        "ethnicity": "other",
        "name": "Hashim"
    },
    {
        "confidence": [
            0.023136913776397705,
            0.9768630266189575
        ],
        "ethnicity": "other",
        "name": "Hassan"
    },
    {
        "confidence": [
            0.02367877960205078,
            0.9763212203979492
        ],
        "ethnicity": "other",
        "name": "Hibah"
    },
    {
        "confidence": [
            0.02352285385131836,
            0.9764771461486816
        ],
        "ethnicity": "other",
        "name": "Hilel"
    },
    {
        "confidence": [
            0.02316725254058838,
            0.9768328666687012
        ],
        "ethnicity": "other",
        "name": "Hud"
    },
    {
        "confidence": [
            0.023131072521209717,
            0.9768689274787903
        ],
        "ethnicity": "other",
        "name": "Humam"
    },
    {
        "confidence": [
            0.023139089345932007,
            0.9768608808517456
        ],
        "ethnicity": "other",
        "name": "Husam"
    },
    {
        "confidence": [
            0.023131072521209717,
            0.9768689274787903
        ],
        "ethnicity": "other",
        "name": "Husam al din"
    },
    {
        "confidence": [
            0.023131072521209717,
            0.9768689274787903
        ],
        "ethnicity": "other",
        "name": "Ibrahim"
    },
    {
        "confidence": [
            0.023452728986740112,
            0.9765473008155823
        ],
        "ethnicity": "other",
        "name": "Id"
    },
    {
        "confidence": [
            0.023807436227798462,
            0.9761925935745239
        ],
        "ethnicity": "other",
        "name": "Idris"
    },
    {
        "confidence": [
            0.023131072521209717,
            0.9768689274787903
        ],
        "ethnicity": "other",
        "name": "Ihsan"
    },
    {
        "confidence": [
            0.023131072521209717,
            0.9768689274787903
        ],
        "ethnicity": "other",
        "name": "Ihtisham"
    },
    {
        "confidence": [
            0.37751278281211853,
            0.6224870681762695
        ],
        "ethnicity": "other",
        "name": "Ikrimah"
    },
    {
        "confidence": [
            0.023443490266799927,
            0.9765565395355225
        ],
        "ethnicity": "other",
        "name": "Ilias"
    },
    {
        "confidence": [
            0.025499314069747925,
            0.9745006561279297
        ],
        "ethnicity": "other",
        "name": "Imad"
    },
    {
        "confidence": [
            0.026372194290161133,
            0.9736277461051941
        ],
        "ethnicity": "other",
        "name": "Imad al Din"
    },
    {
        "confidence": [
            0.023132115602493286,
            0.9768679141998291
        ],
        "ethnicity": "other",
        "name": "Imam"
    },
    {
        "confidence": [
            0.023133575916290283,
            0.9768664836883545
        ],
        "ethnicity": "other",
        "name": "Imtiyaz"
    },
    {
        "confidence": [
            0.023131072521209717,
            0.9768689274787903
        ],
        "ethnicity": "other",
        "name": "In’am"
    },
    {
        "confidence": [
            0.023131072521209717,
            0.9768689274787903
        ],
        "ethnicity": "other",
        "name": "Iqbal"
    },
    {
        "confidence": [
            0.023131072521209717,
            0.9768689274787903
        ],
        "ethnicity": "other",
        "name": "Irfan"
    },
    {
        "confidence": [
            0.023132115602493286,
            0.9768679141998291
        ],
        "ethnicity": "other",
        "name": "Ishaq"
    },
    {
        "confidence": [
            0.024061113595962524,
            0.9759389758110046
        ],
        "ethnicity": "other",
        "name": "Isma’il"
    },
    {
        "confidence": [
            0.023131072521209717,
            0.9768689274787903
        ],
        "ethnicity": "other",
        "name": "Issam"
    },
    {
        "confidence": [
            0.02323848009109497,
            0.9767615795135498
        ],
        "ethnicity": "other",
        "name": "Iyad"
    },
    {
        "confidence": [
            0.024300366640090942,
            0.9756996035575867
        ],
        "ethnicity": "other",
        "name": "Izz al Din"
    },
    {
        "confidence": [
            0.023339658975601196,
            0.9766603112220764
        ],
        "ethnicity": "other",
        "name": "Jabbar"
    },
    {
        "confidence": [
            0.02613121271133423,
            0.9738687872886658
        ],
        "ethnicity": "other",
        "name": "Jabir"
    },
    {
        "confidence": [
            0.02313411235809326,
            0.9768658876419067
        ],
        "ethnicity": "other",
        "name": "Jafar"
    },
    {
        "confidence": [
            0.02315056324005127,
            0.9768494367599487
        ],
        "ethnicity": "other",
        "name": "Jalal"
    },
    {
        "confidence": [
            0.9732869863510132,
            0.02671298384666443
        ],
        "ethnicity": "white",
        "name": "Jaleel"
    },
    {
        "confidence": [
            0.023131221532821655,
            0.976868748664856
        ],
        "ethnicity": "other",
        "name": "Jalil"
    },
    {
        "confidence": [
            0.024717897176742554,
            0.9752820730209351
        ],
        "ethnicity": "other",
        "name": "Jamal"
    },
    {
        "confidence": [
            0.025835901498794556,
            0.9741640686988831
        ],
        "ethnicity": "other",
        "name": "Jameel"
    },
    {
        "confidence": [
            0.023521125316619873,
            0.9764788746833801
        ],
        "ethnicity": "other",
        "name": "Jarir"
    },
    {
        "confidence": [
            0.024753838777542114,
            0.9752460718154907
        ],
        "ethnicity": "other",
        "name": "Jasim"
    },
    {
        "confidence": [
            0.023132264614105225,
            0.9768677353858948
        ],
        "ethnicity": "other",
        "name": "Jaul"
    },
    {
        "confidence": [
            0.02314460277557373,
            0.9768553972244263
        ],
        "ethnicity": "other",
        "name": "Jaun"
    },
    {
        "confidence": [
            0.023143798112869263,
            0.9768562316894531
        ],
        "ethnicity": "other",
        "name": "Jawad"
    },
    {
        "confidence": [
            0.02313140034675598,
            0.9768685102462769
        ],
        "ethnicity": "other",
        "name": "Jawhar"
    },
    {
        "confidence": [
            0.024580836296081543,
            0.9754191637039185
        ],
        "ethnicity": "other",
        "name": "Jed"
    },
    {
        "confidence": [
            0.023131072521209717,
            0.9768689274787903
        ],
        "ethnicity": "other",
        "name": "Jibril"
    },
    {
        "confidence": [
            0.023131072521209717,
            0.9768689274787903
        ],
        "ethnicity": "other",
        "name": "Jihad"
    },
    {
        "confidence": [
            0.023131072521209717,
            0.9768689274787903
        ],
        "ethnicity": "other",
        "name": "Kadeen"
    },
    {
        "confidence": [
            0.026371121406555176,
            0.9736288189888
        ],
        "ethnicity": "other",
        "name": "Kadeer"
    },
    {
        "confidence": [
            0.36107364296913147,
            0.6389263272285461
        ],
        "ethnicity": "other",
        "name": "Kadin"
    },
    {
        "confidence": [
            0.026826947927474976,
            0.9731730222702026
        ],
        "ethnicity": "other",
        "name": "Kadir"
    },
    {
        "confidence": [
            0.023131072521209717,
            0.9768689274787903
        ],
        "ethnicity": "other",
        "name": "Kahil"
    },
    {
        "confidence": [
            0.024460703134536743,
            0.9755393266677856
        ],
        "ethnicity": "other",
        "name": "Kalb"
    },
    {
        "confidence": [
            0.023131132125854492,
            0.9768688678741455
        ],
        "ethnicity": "other",
        "name": "Kalil"
    },
    {
        "confidence": [
            0.023131072521209717,
            0.9768689274787903
        ],
        "ethnicity": "other",
        "name": "Kaliq"
    },
    {
        "confidence": [
            0.023820966482162476,
            0.9761790037155151
        ],
        "ethnicity": "other",
        "name": "Kamal"
    },
    {
        "confidence": [
            0.02359411120414734,
            0.9764058589935303
        ],
        "ethnicity": "other",
        "name": "Kameel"
    },
    {
        "confidence": [
            0.023135900497436523,
            0.9768640995025635
        ],
        "ethnicity": "other",
        "name": "Kaniel"
    },
    {
        "confidence": [
            0.023131072521209717,
            0.9768689274787903
        ],
        "ethnicity": "other",
        "name": "Karam"
    },
    {
        "confidence": [
            0.023739486932754517,
            0.9762605428695679
        ],
        "ethnicity": "other",
        "name": "Kardal"
    },
    {
        "confidence": [
            0.023136764764785767,
            0.9768632650375366
        ],
        "ethnicity": "other",
        "name": "Karif"
    },
    {
        "confidence": [
            0.023229002952575684,
            0.9767710566520691
        ],
        "ethnicity": "other",
        "name": "Karim"
    },
    {
        "confidence": [
            0.023220807313919067,
            0.9767792224884033
        ],
        "ethnicity": "other",
        "name": "Kaseem"
    },
    {
        "confidence": [
            0.9732869863510132,
            0.02671298384666443
        ],
        "ethnicity": "white",
        "name": "Kasib"
    },
    {
        "confidence": [
            0.02313697338104248,
            0.9768630266189575
        ],
        "ethnicity": "other",
        "name": "Kateb"
    },
    {
        "confidence": [
            0.023646771907806396,
            0.9763532876968384
        ],
        "ethnicity": "other",
        "name": "Kedar"
    },
    {
        "confidence": [
            0.023131072521209717,
            0.9768689274787903
        ],
        "ethnicity": "other",
        "name": "Khalil"
    },
    {
        "confidence": [
            0.023131072521209717,
            0.9768689274787903
        ],
        "ethnicity": "other",
        "name": "Labib"
    },
    {
        "confidence": [
            0.028020143508911133,
            0.9719799160957336
        ],
        "ethnicity": "other",
        "name": "Laith"
    },
    {
        "confidence": [
            0.0231342613697052,
            0.9768657088279724
        ],
        "ethnicity": "other",
        "name": "Latif"
    },
    {
        "confidence": [
            0.024551451206207275,
            0.9754485487937927
        ],
        "ethnicity": "other",
        "name": "Layth"
    },
    {
        "confidence": [
            0.1359141767024994,
            0.8640857934951782
        ],
        "ethnicity": "other",
        "name": "Leron"
    },
    {
        "confidence": [
            0.023131072521209717,
            0.9768689274787903
        ],
        "ethnicity": "other",
        "name": "Lu’ay"
    },
    {
        "confidence": [
            0.023131072521209717,
            0.9768689274787903
        ],
        "ethnicity": "other",
        "name": "Lubaid"
    },
    {
        "confidence": [
            0.023854047060012817,
            0.9761460423469543
        ],
        "ethnicity": "other",
        "name": "Lutfi"
    },
    {
        "confidence": [
            0.023131072521209717,
            0.9768689274787903
        ],
        "ethnicity": "other",
        "name": "Ma’mun"
    },
    {
        "confidence": [
            0.02479580044746399,
            0.9752041697502136
        ],
        "ethnicity": "other",
        "name": "Ma’ruf"
    },
    {
        "confidence": [
            0.023131072521209717,
            0.9768689274787903
        ],
        "ethnicity": "other",
        "name": "Madani"
    },
    {
        "confidence": [
            0.023131072521209717,
            0.9768689274787903
        ],
        "ethnicity": "other",
        "name": "Mahbub"
    },
    {
        "confidence": [
            0.023131072521209717,
            0.9768689274787903
        ],
        "ethnicity": "other",
        "name": "Mahdi"
    },
    {
        "confidence": [
            0.023131072521209717,
            0.9768689274787903
        ],
        "ethnicity": "other",
        "name": "Mahir"
    },
    {
        "confidence": [
            0.0231320858001709,
            0.9768679141998291
        ],
        "ethnicity": "other",
        "name": "Mahjub"
    },
    {
        "confidence": [
            0.023131072521209717,
            0.9768689274787903
        ],
        "ethnicity": "other",
        "name": "Mahmud"
    },
    {
        "confidence": [
            0.026102215051651,
            0.9738978147506714
        ],
        "ethnicity": "other",
        "name": "Mahomet"
    },
    {
        "confidence": [
            0.023131072521209717,
            0.9768689274787903
        ],
        "ethnicity": "other",
        "name": "Majid"
    },
    {
        "confidence": [
            0.9732869863510132,
            0.02671298384666443
        ],
        "ethnicity": "white",
        "name": "Malik"
    },
    {
        "confidence": [
            0.023131072521209717,
            0.9768689274787903
        ],
        "ethnicity": "other",
        "name": "Mamdouh"
    },
    {
        "confidence": [
            0.023131072521209717,
            0.9768689274787903
        ],
        "ethnicity": "other",
        "name": "Mandhur"
    },
    {
        "confidence": [
            0.023161500692367554,
            0.9768384695053101
        ],
        "ethnicity": "other",
        "name": "Mansur"
    },
    {
        "confidence": [
            0.023131072521209717,
            0.9768689274787903
        ],
        "ethnicity": "other",
        "name": "Marid"
    },
    {
        "confidence": [
            0.023197323083877563,
            0.9768027067184448
        ],
        "ethnicity": "other",
        "name": "Mashhur"
    },
    {
        "confidence": [
            0.023131072521209717,
            0.9768689274787903
        ],
        "ethnicity": "other",
        "name": "Masud"
    },
    {
        "confidence": [
            0.023131072521209717,
            0.9768689274787903
        ],
        "ethnicity": "other",
        "name": "Mazhar"
    },
    {
        "confidence": [
            0.02313140034675598,
            0.9768686294555664
        ],
        "ethnicity": "other",
        "name": "Mohammed"
    },
    {
        "confidence": [
            0.024678915739059448,
            0.9753211736679077
        ],
        "ethnicity": "other",
        "name": "Mufid"
    },
    {
        "confidence": [
            0.023131072521209717,
            0.9768689274787903
        ],
        "ethnicity": "other",
        "name": "Muhammad"
    },
    {
        "confidence": [
            0.023149490356445312,
            0.9768503904342651
        ],
        "ethnicity": "other",
        "name": "Muhib"
    },
    {
        "confidence": [
            0.023131072521209717,
            0.9768689274787903
        ],
        "ethnicity": "other",
        "name": "Muhsin"
    },
    {
        "confidence": [
            0.023131072521209717,
            0.9768689274787903
        ],
        "ethnicity": "other",
        "name": "Muhtadi"
    },
    {
        "confidence": [
            0.023131072521209717,
            0.9768689274787903
        ],
        "ethnicity": "other",
        "name": "Na’man"
    },
    {
        "confidence": [
            0.023131072521209717,
            0.9768689274787903
        ],
        "ethnicity": "other",
        "name": "Nabeel"
    },
    {
        "confidence": [
            0.023131072521209717,
            0.9768689274787903
        ],
        "ethnicity": "other",
        "name": "Nabhan"
    },
    {
        "confidence": [
            0.023131072521209717,
            0.9768689274787903
        ],
        "ethnicity": "other",
        "name": "Nabih"
    },
    {
        "confidence": [
            0.02354291081428528,
            0.9764571189880371
        ],
        "ethnicity": "other",
        "name": "Nadim"
    },
    {
        "confidence": [
            0.023133963346481323,
            0.9768660068511963
        ],
        "ethnicity": "other",
        "name": "Nadir"
    },
    {
        "confidence": [
            0.023131072521209717,
            0.9768689274787903
        ],
        "ethnicity": "other",
        "name": "Nahid"
    },
    {
        "confidence": [
            0.023133456707000732,
            0.976866602897644
        ],
        "ethnicity": "other",
        "name": "Najeeb"
    },
    {
        "confidence": [
            0.023131072521209717,
            0.9768689274787903
        ],
        "ethnicity": "other",
        "name": "Naji"
    },
    {
        "confidence": [
            0.02313181757926941,
            0.976868212223053
        ],
        "ethnicity": "other",
        "name": "Najjar"
    },
    {
        "confidence": [
            0.023131072521209717,
            0.9768689274787903
        ],
        "ethnicity": "other",
        "name": "Namir"
    },
    {
        "confidence": [
            0.023131072521209717,
            0.9768689274787903
        ],
        "ethnicity": "other",
        "name": "Nashwan"
    },
    {
        "confidence": [
            0.023131072521209717,
            0.9768689274787903
        ],
        "ethnicity": "other",
        "name": "Nasib"
    },
    {
        "confidence": [
            0.02313181757926941,
            0.976868212223053
        ],
        "ethnicity": "other",
        "name": "Nasir"
    },
    {
        "confidence": [
            0.026363223791122437,
            0.9736367464065552
        ],
        "ethnicity": "other",
        "name": "Nidal"
    },
    {
        "confidence": [
            0.023131072521209717,
            0.9768689274787903
        ],
        "ethnicity": "other",
        "name": "Nijad"
    },
    {
        "confidence": [
            0.023131072521209717,
            0.9768689274787903
        ],
        "ethnicity": "other",
        "name": "Nizar"
    },
    {
        "confidence": [
            0.023131072521209717,
            0.9768689274787903
        ],
        "ethnicity": "other",
        "name": "Numair"
    },
    {
        "confidence": [
            0.023753345012664795,
            0.9762466549873352
        ],
        "ethnicity": "other",
        "name": "Omar"
    },
    {
        "confidence": [
            0.023238956928253174,
            0.9767610430717468
        ],
        "ethnicity": "other",
        "name": "Osman"
    },
    {
        "confidence": [
            0.023131072521209717,
            0.9768689274787903
        ],
        "ethnicity": "other",
        "name": "Qabil"
    },
    {
        "confidence": [
            0.02313154935836792,
            0.9768685102462769
        ],
        "ethnicity": "other",
        "name": "Qadim"
    },
    {
        "confidence": [
            0.023132532835006714,
            0.9768674373626709
        ],
        "ethnicity": "other",
        "name": "Qadir"
    },
    {
        "confidence": [
            0.023133277893066406,
            0.9768667221069336
        ],
        "ethnicity": "other",
        "name": "Qamar"
    },
    {
        "confidence": [
            0.052867740392684937,
            0.9471322298049927
        ],
        "ethnicity": "other",
        "name": "Qasim"
    },
    {
        "confidence": [
            0.023131072521209717,
            0.9768689274787903
        ],
        "ethnicity": "other",
        "name": "Qatadah"
    },
    {
        "confidence": [
            0.024664580821990967,
            0.9753354787826538
        ],
        "ethnicity": "other",
        "name": "Quasim"
    },
    {
        "confidence": [
            0.023214489221572876,
            0.9767855405807495
        ],
        "ethnicity": "other",
        "name": "Qudamah"
    },
    {
        "confidence": [
            0.02313181757926941,
            0.976868212223053
        ],
        "ethnicity": "other",
        "name": "Qusay"
    },
    {
        "confidence": [
            0.023131072521209717,
            0.9768689274787903
        ],
        "ethnicity": "other",
        "name": "Qutb"
    },
    {
        "confidence": [
            0.02473500370979309,
            0.9752649068832397
        ],
        "ethnicity": "other",
        "name": "Rafid"
    },
    {
        "confidence": [
            0.023131072521209717,
            0.9768689274787903
        ],
        "ethnicity": "other",
        "name": "Raja"
    },
    {
        "confidence": [
            0.023131072521209717,
            0.9768689274787903
        ],
        "ethnicity": "other",
        "name": "Rajih"
    },
    {
        "confidence": [
            0.02315804362297058,
            0.9768420457839966
        ],
        "ethnicity": "other",
        "name": "Rakin"
    },
    {
        "confidence": [
            0.02313295006752014,
            0.9768669605255127
        ],
        "ethnicity": "other",
        "name": "Ramadan"
    },
    {
        "confidence": [
            0.023131072521209717,
            0.9768689274787903
        ],
        "ethnicity": "other",
        "name": "Rami"
    },
    {
        "confidence": [
            0.023135274648666382,
            0.9768646955490112
        ],
        "ethnicity": "other",
        "name": "Ramzi"
    },
    {
        "confidence": [
            0.023222893476486206,
            0.9767770767211914
        ],
        "ethnicity": "other",
        "name": "Rani"
    },
    {
        "confidence": [
            0.023131072521209717,
            0.9768689274787903
        ],
        "ethnicity": "other",
        "name": "Rashad"
    },
    {
        "confidence": [
            0.02326563000679016,
            0.9767343997955322
        ],
        "ethnicity": "other",
        "name": "Rasil"
    },
    {
        "confidence": [
            0.02317345142364502,
            0.976826548576355
        ],
        "ethnicity": "other",
        "name": "Rasin"
    },
    {
        "confidence": [
            0.02325311303138733,
            0.9767468571662903
        ],
        "ethnicity": "other",
        "name": "Rasmi"
    },
    {
        "confidence": [
            0.06841439008712769,
            0.9315856695175171
        ],
        "ethnicity": "other",
        "name": "Rasul"
    },
    {
        "confidence": [
            0.023131072521209717,
            0.9768689274787903
        ],
        "ethnicity": "other",
        "name": "Ratib"
    },
    {
        "confidence": [
            0.023131072521209717,
            0.9768689274787903
        ],
        "ethnicity": "other",
        "name": "Rayhan"
    },
    {
        "confidence": [
            0.023135721683502197,
            0.9768642783164978
        ],
        "ethnicity": "other",
        "name": "Rayyan"
    },
    {
        "confidence": [
            0.023135274648666382,
            0.9768646955490112
        ],
        "ethnicity": "other",
        "name": "Razin"
    },
    {
        "confidence": [
            0.023131072521209717,
            0.9768689274787903
        ],
        "ethnicity": "other",
        "name": "Rihab"
    },
    {
        "confidence": [
            0.023336708545684814,
            0.9766632318496704
        ],
        "ethnicity": "other",
        "name": "Rimon"
    },
    {
        "confidence": [
            0.023413538932800293,
            0.9765864610671997
        ],
        "ethnicity": "other",
        "name": "Ruhi"
    },
    {
        "confidence": [
            0.02313181757926941,
            0.976868212223053
        ],
        "ethnicity": "other",
        "name": "Rushd"
    },
    {
        "confidence": [
            0.023131877183914185,
            0.9768681526184082
        ],
        "ethnicity": "other",
        "name": "Rushdi"
    },
    {
        "confidence": [
            0.1422131061553955,
            0.8577868938446045
        ],
        "ethnicity": "other",
        "name": "Ruwayd"
    },
    {
        "confidence": [
            0.023131072521209717,
            0.9768689274787903
        ],
        "ethnicity": "other",
        "name": "Sa’adah"
    },
    {
        "confidence": [
            0.02350449562072754,
            0.9764955043792725
        ],
        "ethnicity": "other",
        "name": "Sa’d al Din"
    },
    {
        "confidence": [
            0.023131072521209717,
            0.9768689274787903
        ],
        "ethnicity": "other",
        "name": "Sa’ib"
    },
    {
        "confidence": [
            0.023131072521209717,
            0.9768689274787903
        ],
        "ethnicity": "other",
        "name": "Saad"
    },
    {
        "confidence": [
            0.023333460092544556,
            0.9766665101051331
        ],
        "ethnicity": "other",
        "name": "Sabir"
    },
    {
        "confidence": [
            0.02313724160194397,
            0.9768627882003784
        ],
        "ethnicity": "other",
        "name": "Sadid"
    },
    {
        "confidence": [
            0.023131072521209717,
            0.9768689274787903
        ],
        "ethnicity": "other",
        "name": "Sadiq"
    },
    {
        "confidence": [
            0.023131072521209717,
            0.9768689274787903
        ],
        "ethnicity": "other",
        "name": "Safiy al Din"
    },
    {
        "confidence": [
            0.023131102323532104,
            0.9768688678741455
        ],
        "ethnicity": "other",
        "name": "Safuh"
    },
    {
        "confidence": [
            0.023131072521209717,
            0.9768689274787903
        ],
        "ethnicity": "other",
        "name": "Sahib"
    },
    {
        "confidence": [
            0.023136913776397705,
            0.9768630266189575
        ],
        "ethnicity": "other",
        "name": "Sahir"
    },
    {
        "confidence": [
            0.023131072521209717,
            0.9768689274787903
        ],
        "ethnicity": "other",
        "name": "Sajid"
    },
    {
        "confidence": [
            0.023512065410614014,
            0.9764879941940308
        ],
        "ethnicity": "other",
        "name": "Sakhr"
    },
    {
        "confidence": [
            0.023131072521209717,
            0.9768689274787903
        ],
        "ethnicity": "other",
        "name": "Salah"
    },
    {
        "confidence": [
            0.023131072521209717,
            0.9768689274787903
        ],
        "ethnicity": "other",
        "name": "Salamah"
    },
    {
        "confidence": [
            0.026793181896209717,
            0.9732068181037903
        ],
        "ethnicity": "other",
        "name": "Saleh"
    },
    {
        "confidence": [
            0.023131072521209717,
            0.9768689274787903
        ],
        "ethnicity": "other",
        "name": "Salman"
    },
    {
        "confidence": [
            0.9732869863510132,
            0.02671298384666443
        ],
        "ethnicity": "white",
        "name": "Sameer"
    },
    {
        "confidence": [
            0.0231342613697052,
            0.9768657088279724
        ],
        "ethnicity": "other",
        "name": "Sami"
    },
    {
        "confidence": [
            0.024316757917404175,
            0.9756832122802734
        ],
        "ethnicity": "other",
        "name": "Samien"
    },
    {
        "confidence": [
            0.02322971820831299,
            0.9767704010009766
        ],
        "ethnicity": "other",
        "name": "Samih"
    },
    {
        "confidence": [
            0.023131072521209717,
            0.9768689274787903
        ],
        "ethnicity": "other",
        "name": "Saqr"
    },
    {
        "confidence": [
            0.023131072521209717,
            0.9768689274787903
        ],
        "ethnicity": "other",
        "name": "Sariyah"
    },
    {
        "confidence": [
            0.027402907609939575,
            0.9725971221923828
        ],
        "ethnicity": "other",
        "name": "Sarni"
    },
    {
        "confidence": [
            0.023131072521209717,
            0.9768689274787903
        ],
        "ethnicity": "other",
        "name": "Saud"
    },
    {
        "confidence": [
            0.9151899814605713,
            0.08481001853942871
        ],
        "ethnicity": "white",
        "name": "Seif"
    },
    {
        "confidence": [
            0.023131072521209717,
            0.9768689274787903
        ],
        "ethnicity": "other",
        "name": "Selim"
    },
    {
        "confidence": [
            0.023227185010910034,
            0.9767727851867676
        ],
        "ethnicity": "other",
        "name": "Seyed"
    },
    {
        "confidence": [
            0.023132532835006714,
            0.9768674373626709
        ],
        "ethnicity": "other",
        "name": "Shadi"
    },
    {
        "confidence": [
            0.023131072521209717,
            0.9768689274787903
        ],
        "ethnicity": "other",
        "name": "Shadin"
    },
    {
        "confidence": [
            0.023132532835006714,
            0.9768674373626709
        ],
        "ethnicity": "other",
        "name": "Taj"
    },
    {
        "confidence": [
            0.02350202202796936,
            0.976498007774353
        ],
        "ethnicity": "other",
        "name": "Talal"
    },
    {
        "confidence": [
            0.023131072521209717,
            0.9768689274787903
        ],
        "ethnicity": "other",
        "name": "Talib"
    },
    {
        "confidence": [
            0.023131072521209717,
            0.9768689274787903
        ],
        "ethnicity": "other",
        "name": "Tamam"
    },
    {
        "confidence": [
            0.02313181757926941,
            0.976868212223053
        ],
        "ethnicity": "other",
        "name": "Tamir"
    },
    {
        "confidence": [
            0.02313464879989624,
            0.9768653512001038
        ],
        "ethnicity": "other",
        "name": "Tarif"
    },
    {
        "confidence": [
            0.023131072521209717,
            0.9768689274787903
        ],
        "ethnicity": "other",
        "name": "Ubaid"
    },
    {
        "confidence": [
            0.023206472396850586,
            0.9767935276031494
        ],
        "ethnicity": "other",
        "name": "Umar"
    },
    {
        "confidence": [
            0.023131072521209717,
            0.9768689274787903
        ],
        "ethnicity": "other",
        "name": "Umarah"
    },
    {
        "confidence": [
            0.023131072521209717,
            0.9768689274787903
        ],
        "ethnicity": "other",
        "name": "Urwah"
    },
    {
        "confidence": [
            0.023131072521209717,
            0.9768689274787903
        ],
        "ethnicity": "other",
        "name": "Wadi"
    },
    {
        "confidence": [
            0.023131072521209717,
            0.9768689274787903
        ],
        "ethnicity": "other",
        "name": "Wajdi"
    },
    {
        "confidence": [
            0.023131072521209717,
            0.9768689274787903
        ],
        "ethnicity": "other",
        "name": "Wajid"
    },
    {
        "confidence": [
            0.023131072521209717,
            0.9768689274787903
        ],
        "ethnicity": "other",
        "name": "Wajih"
    },
    {
        "confidence": [
            0.02332979440689087,
            0.9766701459884644
        ],
        "ethnicity": "other",
        "name": "Wakil"
    },
    {
        "confidence": [
            0.024507522583007812,
            0.9754924774169922
        ],
        "ethnicity": "other",
        "name": "Walid"
    },
    {
        "confidence": [
            0.023131072521209717,
            0.9768689274787903
        ],
        "ethnicity": "other",
        "name": "Yazan"
    },
    {
        "confidence": [
            0.023135632276535034,
            0.9768644571304321
        ],
        "ethnicity": "other",
        "name": "Yazeed"
    },
    {
        "confidence": [
            0.023213565349578857,
            0.9767864346504211
        ],
        "ethnicity": "other",
        "name": "Yoonus"
    },
    {
        "confidence": [
            0.023135721683502197,
            0.9768642783164978
        ],
        "ethnicity": "other",
        "name": "Youssef"
    },
    {
        "confidence": [
            0.023131221532821655,
            0.976868748664856
        ],
        "ethnicity": "other",
        "name": "Yushua"
    },
    {
        "confidence": [
            0.02370738983154297,
            0.976292610168457
        ],
        "ethnicity": "other",
        "name": "Yusri"
    },
    {
        "confidence": [
            0.023133575916290283,
            0.9768664836883545
        ],
        "ethnicity": "other",
        "name": "Yusuf"
    },
    {
        "confidence": [
            0.023132532835006714,
            0.9768674373626709
        ],
        "ethnicity": "other",
        "name": "Zafar"
    },
    {
        "confidence": [
            0.023131072521209717,
            0.9768689274787903
        ],
        "ethnicity": "other",
        "name": "Zaid"
    },
    {
        "confidence": [
            0.023138046264648438,
            0.9768619537353516
        ],
        "ethnicity": "other",
        "name": "Zaim"
    },
    {
        "confidence": [
            0.023131072521209717,
            0.9768689274787903
        ],
        "ethnicity": "other",
        "name": "Zakwan"
    },
    {
        "confidence": [
            0.02439132332801819,
            0.9756087064743042
        ],
        "ethnicity": "other",
        "name": "Zarif"
    },
    {
        "confidence": [
            0.023131072521209717,
            0.9768689274787903
        ],
        "ethnicity": "other",
        "name": "Zayn"
    },
    {
        "confidence": [
            0.02335911989212036,
            0.9766408801078796
        ],
        "ethnicity": "other",
        "name": "Zimraan"
    },
    {
        "confidence": [
            0.023230386897921562,
            0.9767696261405945
        ],
        "ethnicity": "other",
        "name": "Zoltan"
    },
    {
        "confidence": [
            0.024410856887698174,
            0.9755891561508179
        ],
        "ethnicity": "other",
        "name": "Zubayr"
    }
]